graphene_gis/__init__.py
graphene_gis/converter.py
graphene_gis/scalars.py
graphene_gis-0.0.2.dist-info/LICENSE
graphene_gis-0.0.2.dist-info/METADATA
graphene_gis-0.0.2.dist-info/WHEEL
graphene_gis-0.0.2.dist-info/top_level.txt
graphene_gis-0.0.2.dist-info/RECORD
